{"name":"","id":"automation-demo-site;","testSteps":[{"number":1,"description":"Given than Yaiseth wants to registration in the Automation Demo Site page","duration":6598,"startTime":"2021-12-15T23:10:00.184-05:00[America/Bogota]","screenshots":[{"screenshot":"a228c86dbd1e6c015b3a6ec79e6306f37c6214ebda8861d8fa104a21090822a3.png","timeStamp":1639627806782}],"result":"SUCCESS","precondition":false,"level":0,"lineNumber":0,"children":[{"number":2,"description":"Yaiseth open up","duration":5927,"startTime":"2021-12-15T23:10:00.842-05:00[America/Bogota]","screenshots":[{"screenshot":"a228c86dbd1e6c015b3a6ec79e6306f37c6214ebda8861d8fa104a21090822a3.png","timeStamp":1639627806769}],"result":"SUCCESS","precondition":false,"level":1,"lineNumber":0,"children":[{"number":3,"description":"Yaiseth opens the Automation demo site page","duration":5893,"startTime":"2021-12-15T23:10:00.858-05:00[America/Bogota]","screenshots":[{"screenshot":"a228c86dbd1e6c015b3a6ec79e6306f37c6214ebda8861d8fa104a21090822a3.png","timeStamp":1639627806748}],"result":"SUCCESS","precondition":false,"level":2,"lineNumber":0}]}]},{"number":4,"description":"When fills in all requested fields","duration":16011,"startTime":"2021-12-15T23:10:06.782-05:00[America/Bogota]","screenshots":[{"screenshot":"59321f9826ef47ce913dbb6758147224481c91914daab61b09c2187632eb20c9.png","timeStamp":1639627822793}],"result":"SUCCESS","precondition":false,"level":0,"lineNumber":0,"children":[{"number":5,"description":"Yaiseth login on demo","duration":15975,"startTime":"2021-12-15T23:10:06.799-05:00[America/Bogota]","screenshots":[{"screenshot":"59321f9826ef47ce913dbb6758147224481c91914daab61b09c2187632eb20c9.png","timeStamp":1639627822774}],"result":"SUCCESS","precondition":false,"level":1,"lineNumber":0,"children":[{"number":6,"description":"Yaiseth clicks on button skip login section","duration":5213,"startTime":"2021-12-15T23:10:06.931-05:00[America/Bogota]","screenshots":[{"screenshot":"a951f103e32279abbf69d0d3c6f02a5c3e7cab5b7aae6c648e89c63835a04ef9.png","timeStamp":1639627812144}],"result":"SUCCESS","precondition":false,"level":2,"lineNumber":0},{"number":7,"description":"Yaiseth enters \u0027Diana\u0027 into Insert Name","duration":1039,"startTime":"2021-12-15T23:10:12.144-05:00[America/Bogota]","screenshots":[{"screenshot":"0419c5dff2a0dc83780613bf141a94af9a38c9c9e30bf705133cb3fe64a846d3.png","timeStamp":1639627813183}],"result":"SUCCESS","precondition":false,"level":2,"lineNumber":0},{"number":8,"description":"Yaiseth enters \u0027Victoria\u0027 into Insert LastName","duration":595,"startTime":"2021-12-15T23:10:13.186-05:00[America/Bogota]","screenshots":[{"screenshot":"29ae9eb4b5d9a73fa5e61d7570a3aba9c4b0829a818c8b566ccd7a596d6bc6c7.png","timeStamp":1639627813781}],"result":"SUCCESS","precondition":false,"level":2,"lineNumber":0},{"number":9,"description":"Yaiseth enters \u0027Panama Oeste\u0027 into Insert your Address","duration":767,"startTime":"2021-12-15T23:10:13.782-05:00[America/Bogota]","screenshots":[{"screenshot":"0071fe02c79791527c50fa15eff57b168b6e881c9b64c320ab16bc3894cd6f58.png","timeStamp":1639627814549}],"result":"SUCCESS","precondition":false,"level":2,"lineNumber":0},{"number":10,"description":"Yaiseth enters \u0027diana@gmail.com\u0027 into write email","duration":759,"startTime":"2021-12-15T23:10:14.549-05:00[America/Bogota]","screenshots":[{"screenshot":"9b5ae7d840c8d3287a0f6a6224f86a839c757d7657d5a3e00fd9a68bd3c59481.png","timeStamp":1639627815308}],"result":"SUCCESS","precondition":false,"level":2,"lineNumber":0},{"number":11,"description":"Yaiseth enters \u00277739600726\u0027 into Insert the phone number","duration":639,"startTime":"2021-12-15T23:10:15.310-05:00[America/Bogota]","screenshots":[{"screenshot":"687e75966330f17d2d5214eeb28892a1d22d4cbacef6d90a04594a77e5389dca.png","timeStamp":1639627815949}],"result":"SUCCESS","precondition":false,"level":2,"lineNumber":0},{"number":12,"description":"Yaiseth clicks on Select gender","duration":436,"startTime":"2021-12-15T23:10:15.952-05:00[America/Bogota]","screenshots":[{"screenshot":"06ecbd13aa23f5ba9dd00ea07295c199cac2475f03a6b0f29dfb8f8776bbed7f.png","timeStamp":1639627816388}],"result":"SUCCESS","precondition":false,"level":2,"lineNumber":0},{"number":13,"description":"Yaiseth clicks on Click to skill drop","duration":488,"startTime":"2021-12-15T23:10:16.403-05:00[America/Bogota]","screenshots":[{"screenshot":"eca2d8dc8ca0805d169eb034390a52b6c247883f7707d825910a6dabae70b5a9.png","timeStamp":1639627816890}],"result":"SUCCESS","precondition":false,"level":2,"lineNumber":0},{"number":14,"description":"Yaiseth clicks on Select Skill","duration":416,"startTime":"2021-12-15T23:10:16.891-05:00[America/Bogota]","screenshots":[{"screenshot":"eca2d8dc8ca0805d169eb034390a52b6c247883f7707d825910a6dabae70b5a9.png","timeStamp":1639627817307}],"result":"SUCCESS","precondition":false,"level":2,"lineNumber":0},{"number":15,"description":"Yaiseth clicks on Click to Country drop","duration":512,"startTime":"2021-12-15T23:10:17.308-05:00[America/Bogota]","screenshots":[{"screenshot":"a43b76666493e3a1991d4b1aaafd6330e657e8efbb13fc864ad03886ea94195b.png","timeStamp":1639627817820}],"result":"SUCCESS","precondition":false,"level":2,"lineNumber":0},{"number":16,"description":"Yaiseth enters \u0027United States of America\u0027 into Select Country","duration":595,"startTime":"2021-12-15T23:10:17.823-05:00[America/Bogota]","screenshots":[{"screenshot":"04f6af1abebea7350ad20ce0e36beccf4f15a249c4e4be211198ff07052ef866.png","timeStamp":1639627818418}],"result":"SUCCESS","precondition":false,"level":2,"lineNumber":0},{"number":17,"description":"Yaiseth selects 1994 in Select his year of birth","duration":458,"startTime":"2021-12-15T23:10:18.421-05:00[America/Bogota]","screenshots":[{"screenshot":"42a905611639d10e64c153eb43b07fe81b5a208c13226fd4c71fcf6a050e3b34.png","timeStamp":1639627818879}],"result":"SUCCESS","precondition":false,"level":2,"lineNumber":0},{"number":18,"description":"Yaiseth clicks on Select drop Month","duration":407,"startTime":"2021-12-15T23:10:18.885-05:00[America/Bogota]","screenshots":[{"screenshot":"9f89e54545dec0b34ef00406112441de77528c9a8295e468a8cfa42bcd18678e.png","timeStamp":1639627819292}],"result":"SUCCESS","precondition":false,"level":2,"lineNumber":0},{"number":19,"description":"Yaiseth clicks on Select his birthday day","duration":491,"startTime":"2021-12-15T23:10:19.301-05:00[America/Bogota]","screenshots":[{"screenshot":"4e0844c2603da7833235630e1e7924b68857720263fd5d8de6f40bcb794decd1.png","timeStamp":1639627819792}],"result":"SUCCESS","precondition":false,"level":2,"lineNumber":0},{"number":20,"description":"Yaiseth clicks on Write his password","duration":599,"startTime":"2021-12-15T23:10:19.809-05:00[America/Bogota]","screenshots":[{"screenshot":"ecd178436b43f73ad3dc523f37e31daed46c36edad6352b74f07222b0e9e1986.png","timeStamp":1639627820408}],"result":"SUCCESS","precondition":false,"level":2,"lineNumber":0},{"number":21,"description":"Yaiseth enters \u0027Abcd1234\u0027 into Write his password","duration":709,"startTime":"2021-12-15T23:10:20.424-05:00[America/Bogota]","screenshots":[{"screenshot":"9d32fca4ecdc509f927a53ebcf40d425ad2d077596da34146a96199e5f5b1391.png","timeStamp":1639627821133}],"result":"SUCCESS","precondition":false,"level":2,"lineNumber":0},{"number":22,"description":"Yaiseth enters \u0027Abcd1234\u0027 into Write his password again","duration":774,"startTime":"2021-12-15T23:10:21.148-05:00[America/Bogota]","screenshots":[{"screenshot":"73b36af932cd33958e25b13123c21728390fefe0839657c0f5014c9670b1688e.png","timeStamp":1639627821922}],"result":"SUCCESS","precondition":false,"level":2,"lineNumber":0},{"number":23,"description":"Yaiseth clicks on button submit register","duration":829,"startTime":"2021-12-15T23:10:21.922-05:00[America/Bogota]","screenshots":[{"screenshot":"59321f9826ef47ce913dbb6758147224481c91914daab61b09c2187632eb20c9.png","timeStamp":1639627822751}],"result":"SUCCESS","precondition":false,"level":2,"lineNumber":0}]}]},{"number":24,"description":"Then complete all the field","duration":324,"startTime":"2021-12-15T23:10:22.801-05:00[America/Bogota]","screenshots":[{"screenshot":"a5761fafaecb0cf6d86f53ccd14766a7bb7112792daaff56bd53b5eba2a4f7e5.png","timeStamp":1639627823125}],"result":"SUCCESS","precondition":false,"level":0,"lineNumber":0}],"userStory":{"id":"automation-demo-site","storyName":"Automation Demo Site","path":"src/test/resources/feature/retoTecnico.feature","narrative":"    As a user, I want to complete my registration in the page Automation Demo Site","type":"feature"},"featureTag":{"name":"Feature/Automation Demo Site","type":"feature","displayName":"Feature/Automation Demo Site"},"title":"","tags":[{"name":"scenario1","type":"tag","displayName":"scenario1"},{"name":"stories","type":"tag","displayName":"stories"}],"startTime":"2021-12-15T23:10:00.047-05:00[America/Bogota]","duration":23091,"projectKey":"","sessionId":"4638b95f89ba5f08fd30d0d6077d9ffd","driver":"chrome:yaiseth","isManualTestingUpToDate":false,"manual":false,"testSource":"Cucumber","actors":[{"name":"Yaiseth","can":["browse the web"]}],"result":"SUCCESS"}